mailbox_org_api/APIClient.py
mailbox_org_api/APIError.py
mailbox_org_api/Account.py
mailbox_org_api/Invoice.py
mailbox_org_api/Mail.py
mailbox_org_api/__init__.py
mailbox_org_api-1.3.2.dist-info/licenses/LICENSE
tests/TestAPIClient.py
tests/TestAccount.py
tests/TestInvoice.py
tests/TestMail.py
tests/__init__.py
mailbox_org_api-1.3.2.dist-info/METADATA
mailbox_org_api-1.3.2.dist-info/WHEEL
mailbox_org_api-1.3.2.dist-info/top_level.txt
mailbox_org_api-1.3.2.dist-info/RECORD
