Metadata-Version: 2.4
Name: mailbox-org-api
Version: 1.3.2
Summary: A library to access the mailbox.org Business API.
Author: Hendrik Schlange
Author-email: Hendrik Schlange <mail@heshsum.de>
Project-URL: Homepage, https://github.com/heshsum/mailbox-org-api
Project-URL: Issues, https://github.com/heshsum/mailbox-org-api/issues
Classifier: Programming Language :: Python :: 3
Classifier: License :: OSI Approved :: MIT License
Classifier: Operating System :: OS Independent
Requires-Python: >=3.8
License-File: LICENSE
Dynamic: author
Dynamic: license-file
